MANIFEST.in
README
README.md
setup.py
packagecore/VERSION
packagecore/__init__.py
packagecore/__main__.py
packagecore/builddata.py
packagecore/buildvariables.py
packagecore/buildvariables_test.py
packagecore/configfile.py
packagecore/configparser.py
packagecore/configparser_test.py
packagecore/distributions.py
packagecore/docker.py
packagecore/docker_test.py
packagecore/dpkg.py
packagecore/dpkg_test.py
packagecore/packager.py
packagecore/pkgbuild.py
packagecore/pkgbuild_test.py
packagecore/rpm.py
packagecore/rpm_test.py
packagecore/scriptfile.py
packagecore/scriptfile_test.py
packagecore.egg-info/PKG-INFO
packagecore.egg-info/SOURCES.txt
packagecore.egg-info/dependency_links.txt
packagecore.egg-info/entry_points.txt
packagecore.egg-info/requires.txt
packagecore.egg-info/top_level.txt