Metadata-Version: 2.1
Name: packagecore
Version: 0.11.1
Summary: Utility for building Linux packages for multiple distributions.
Home-page: https://github.com/bytepackager/packagecore
Author: Dominique LaSalle
Author-email: packagecore@solidlake.com
License: GPL2
Platform: UNKNOWN
Requires-Python: >=3.0
